vertx/__init__.py
vertx/__main__.py
vertx/eventbus.py
vertx_python_client-0.4.2.dist-info/LICENSE
vertx_python_client-0.4.2.dist-info/METADATA
vertx_python_client-0.4.2.dist-info/WHEEL
vertx_python_client-0.4.2.dist-info/top_level.txt
vertx_python_client-0.4.2.dist-info/RECORD
