Metadata-Version: 2.1
Name: vertx-python-client
Version: 0.4.2
Summary: An asynchronous TCP eventbus Python client
Home-page: https://github.com/dapangmao/vertx-python-client
Author: dapangmao
Author-email: hchao8@gmail.com
License: MIT
Platform: UNKNOWN
Classifier: License :: OSI Approved :: MIT License
Classifier: Programming Language :: Python :: 3
Requires-Python: >=3.6
